onchfs/__init__.py
onchfs/__main__.py
onchfs/cli.py
onchfs/client.py
onchfs/config.py
onchfs/content_store.tz
onchfs/deploy.py
onchfs/onchfs.tz
onchfs/py.typed
onchfs/resolver.py
onchfs/reveal_utils.py
onchfs/types.py
onchfs/uploader.py
onchfs/utils.py
pyonchfs-0.1.7.dist-info/licenses/LICENSE
pyonchfs-0.1.7.dist-info/METADATA
pyonchfs-0.1.7.dist-info/WHEEL
pyonchfs-0.1.7.dist-info/entry_points.txt
pyonchfs-0.1.7.dist-info/top_level.txt
pyonchfs-0.1.7.dist-info/RECORD
