Metadata-Version: 2.4
Name: pyonchfs
Version: 0.1.7
Summary: Python client and CLI for the OnchFS (On-Chain File System) protocol on Tezos blockchain
Author-email: "objkt.com" <hi@objkt.com>
Maintainer-email: "objkt.com" <hi@objkt.com>
License-Expression: MIT
Project-URL: Homepage, https://github.com/objkt-com/pyonchfs
Project-URL: Repository, https://github.com/objkt-com/pyonchfs
Project-URL: Documentation, https://github.com/objkt-com/pyonchfs#readme
Project-URL: Bug Tracker, https://github.com/objkt-com/pyonchfs/issues
Keywords: tezos,blockchain,onchfs,file-system,storage,ipfs-alternative
Classifier: Development Status :: 4 - Beta
Classifier: Intended Audience :: Developers
Classifier: Operating System :: OS Independent
Classifier: Programming Language :: Python :: 3
Classifier: Programming Language :: Python :: 3.8
Classifier: Programming Language :: Python :: 3.9
Classifier: Programming Language :: Python :: 3.10
Classifier: Programming Language :: Python :: 3.11
Classifier: Programming Language :: Python :: 3.12
Classifier: Topic :: Software Development :: Libraries :: Python Modules
Classifier: Topic :: System :: Filesystems
Classifier: Topic :: Internet :: WWW/HTTP
Classifier: Topic :: Security :: Cryptography
Classifier: Environment :: Console
Requires-Python: >=3.8
License-File: LICENSE
Requires-Dist: pytezos>=3.10.0
Requires-Dist: hpack>=4.0.0
Requires-Dist: pycryptodome>=3.15.0
Provides-Extra: dev
Requires-Dist: pytest>=7.0.0; extra == "dev"
Requires-Dist: pytest-cov>=4.0.0; extra == "dev"
Requires-Dist: black>=22.0.0; extra == "dev"
Requires-Dist: flake8>=5.0.0; extra == "dev"
Requires-Dist: mypy>=1.0.0; extra == "dev"
Requires-Dist: pylint>=3.0.0; extra == "dev"
Requires-Dist: build>=0.8.0; extra == "dev"
Requires-Dist: twine>=4.0.0; extra == "dev"
Dynamic: license-file
